parallel_requests/__init__.py
parallel_requests/base_requests.py
parallel_requests/session.py
tests/__init__.py
tests/conftest.py
tests/test_base_requests.py
tests/test_session.py
parallel_requests-0.0.1.dist-info/METADATA
parallel_requests-0.0.1.dist-info/WHEEL
parallel_requests-0.0.1.dist-info/top_level.txt
parallel_requests-0.0.1.dist-info/RECORD
