Metadata-Version: 2.1
Name: parallel-requests
Version: 0.0.1
Summary: A small example package
Home-page: https://github.com/Kel0/parallel_requests
Author: Kel0
Author-email: rickeyfsimple@example.com
License: UNKNOWN
Platform: UNKNOWN
Classifier: Programming Language :: Python :: 3
Requires-Python: >3.6
